undouble/__init__.py
undouble/examples.py
undouble/undouble.py
undouble-1.4.11.dist-info/licenses/LICENSE
undouble-1.4.11.dist-info/METADATA
undouble-1.4.11.dist-info/WHEEL
undouble-1.4.11.dist-info/top_level.txt
undouble-1.4.11.dist-info/RECORD
