Metadata-Version: 2.4
Name: undouble
Version: 1.4.11
Summary: Undouble is a Python package to detect (near-)identical images.
Author-email: Erdogan Taskesen <erdogant@gmail.com>
License-Expression: MIT
Project-URL: Homepage, https://erdogant.github.io/undouble
Project-URL: Download, https://github.com/erdogant/undouble/archive/{version}.tar.gz
Keywords: images,duplicates,identical
Classifier: Programming Language :: Python :: 3
Classifier: Operating System :: OS Independent
Classifier: Intended Audience :: Education
Classifier: Intended Audience :: Science/Research
Classifier: Operating System :: Unix
Classifier: Operating System :: Microsoft :: Windows
Classifier: Operating System :: MacOS
Classifier: Topic :: Scientific/Engineering :: Artificial Intelligence
Requires-Python: >=3
License-File: LICENSE
Requires-Dist: matplotlib
Requires-Dist: numpy
Requires-Dist: tqdm
Requires-Dist: clustimage>=1.6.6
Requires-Dist: ismember
Requires-Dist: datazets>=1.0.0
Dynamic: license-file
